lupyne/__init__.py
lupyne/py.typed
lupyne/engine/__init__.py
lupyne/engine/analyzers.py
lupyne/engine/documents.py
lupyne/engine/indexers.py
lupyne/engine/queries.py
lupyne/engine/utils.py
lupyne/services/__init__.py
lupyne/services/base.py
lupyne/services/graphql.py
lupyne/services/rest.py
lupyne/services/settings.py
lupyne-3.3.dist-info/LICENSE.txt
lupyne-3.3.dist-info/METADATA
lupyne-3.3.dist-info/WHEEL
lupyne-3.3.dist-info/top_level.txt
lupyne-3.3.dist-info/RECORD
