Metadata-Version: 2.1
Name: lupyne
Version: 3.3
Summary: Pythonic search engine based on PyLucene.
Author-email: Aric Coady <aric.coady@gmail.com>
License: Copyright 2022 Aric Coady
Project-URL: Homepage, https://github.com/coady/lupyne
Project-URL: Documentation, https://coady.github.io/lupyne
Project-URL: Changelog, https://github.com/coady/lupyne/blob/main/CHANGELOG.md
Project-URL: Issues, https://github.com/coady/lupyne/issues
Keywords: lucene,pylucene
Classifier: Development Status :: 6 - Mature
Classifier: Intended Audience :: Developers
Classifier: License :: OSI Approved :: Apache Software License
Classifier: Operating System :: OS Independent
Classifier: Programming Language :: Python :: 3
Classifier: Programming Language :: Python :: 3.9
Classifier: Programming Language :: Python :: 3.10
Classifier: Programming Language :: Python :: 3.11
Classifier: Programming Language :: Python :: 3.12
Classifier: Programming Language :: Python :: 3.13
Classifier: Topic :: Internet :: WWW/HTTP :: HTTP Servers
Classifier: Topic :: Internet :: WWW/HTTP :: Indexing/Search
Classifier: Topic :: Software Development :: Libraries :: Python Modules
Classifier: Topic :: Text Processing :: Indexing
Classifier: Typing :: Typed
Requires-Python: >=3.9
License-File: LICENSE.txt
Provides-Extra: graphql
Requires-Dist: strawberry-graphql[asgi] >=0.221 ; extra == 'graphql'
Provides-Extra: rest
Requires-Dist: fastapi ; extra == 'rest'
